agent1c_metrics/__init__.py
agent1c_metrics/__main__.py
agent1c_metrics/api/metrics.py
agent1c_metrics/api/settings_api.py
agent1c_metrics/config.yaml
agent1c_metrics/core/utils.py
agent1c_metrics/read1c.py
agent1c_metrics/reader.py
agent1c_metrics/service.py
agent1c_metrics/viewer.py
agent1c_metrics-0.5.2.dist-info/LICENSE
agent1c_metrics-0.5.2.dist-info/METADATA
agent1c_metrics-0.5.2.dist-info/WHEEL
agent1c_metrics-0.5.2.dist-info/entry_points.txt
agent1c_metrics-0.5.2.dist-info/RECORD
